config/alldb_init.py
config/conf.py
db/database.py
db/project.py
db/update_db.py
scripts/__init__.py
scripts/eva.py
annoeva-0.1.0.dist-info/LICENSE
annoeva-0.1.0.dist-info/METADATA
annoeva-0.1.0.dist-info/WHEEL
annoeva-0.1.0.dist-info/top_level.txt
annoeva-0.1.0.dist-info/RECORD
