Metadata-Version: 2.2
Name: annoeva
Version: 0.1.0
Summary: A command line utility for managing and executing shell scripts with enhanced logging and formatting
Author-email: Yuan Zan <yfinddream@gmail.com>
License: MIT
Requires-Python: <4.0,>=3.8.1
License-File: LICENSE
Requires-Dist: colorama<0.5.0,>=0.4.6
Requires-Dist: PyYAML<7.0,>=6.0
Requires-Dist: pandas<3.0.0,>=2.0.0
Requires-Dist: sphinxcontrib-mermaid<2.0.0,>=1.0.0
